{
  "initial_balance": 50000.0,
  "cash": 18658.822479934694,
  "positions": {
    "UNH": {
      "shares": 23,
      "entry_price": 408.52,
      "peak_price": 415.53,
      "entry_date": "2026-06-12",
      "entry_conf": 0.55,
      "entry_pred_pct": 3.89
    },
    "INTC": {
      "shares": 23,
      "entry_price": 131.65,
      "peak_price": 132.87,
      "entry_date": "2026-06-24",
      "entry_conf": 0.65,
      "entry_pred_pct": 8.76
    },
    "DIA": {
      "shares": 18,
      "entry_price": 518.52,
      "peak_price": 519.26,
      "entry_date": "2026-06-24",
      "entry_conf": 0.575,
      "entry_pred_pct": 1.19
    },
    "AMD": {
      "shares": 7,
      "entry_price": 532.57,
      "peak_price": 532.57,
      "entry_date": "2026-06-25",
      "entry_conf": 0.55,
      "entry_pred_pct": 9.35
    },
    "SMH": {
      "shares": 6,
      "entry_price": 636.88,
      "peak_price": 636.88,
      "entry_date": "2026-06-25",
      "entry_conf": 0.55,
      "entry_pred_pct": 5.43
    }
  },
  "trades": [
    {
      "date": "2026-03-06",
      "ticker": "SMH",
      "action": "BUY",
      "shares": 25,
      "price": 395.35,
      "value": 9883.75,
      "pnl": null,
      "pred_pct": 7.55,
      "confidence": 0.575,
      "reason": "Top pick #1, conf=57%, pred=+7.5%"
    },
    {
      "date": "2026-03-06",
      "ticker": "LLY",
      "action": "BUY",
      "shares": 10,
      "price": 983.26,
      "value": 9832.6,
      "pnl": null,
      "pred_pct": 4.53,
      "confidence": 0.575,
      "reason": "Top pick #2, conf=57%, pred=+4.5%"
    },
    {
      "date": "2026-03-06",
      "ticker": "XOM",
      "action": "BUY",
      "shares": 66,
      "price": 150.76,
      "value": 9950.16,
      "pnl": null,
      "pred_pct": 3.78,
      "confidence": 0.575,
      "reason": "Top pick #3, conf=57%, pred=+3.8%"
    },
    {
      "date": "2026-03-06",
      "ticker": "GLD",
      "action": "BUY",
      "shares": 21,
      "price": 466.13,
      "value": 9788.73,
      "pnl": null,
      "pred_pct": 3.75,
      "confidence": 0.55,
      "reason": "Top pick #4, conf=55%, pred=+3.8%"
    },
    {
      "date": "2026-03-06",
      "ticker": "BAC",
      "action": "BUY",
      "shares": 200,
      "price": 49.81,
      "value": 9962.0,
      "pnl": null,
      "pred_pct": 2.84,
      "confidence": 0.6,
      "reason": "Top pick #5, conf=60%, pred=+2.8%"
    },
    {
      "date": "2026-03-10",
      "ticker": "SMH",
      "action": "SELL",
      "shares": 25,
      "price": 394.37,
      "value": 9859.25,
      "pnl": -24.5,
      "reason": "Dropped from top picks"
    },
    {
      "date": "2026-03-10",
      "ticker": "LLY",
      "action": "SELL",
      "shares": 10,
      "price": 1008.39,
      "value": 10083.9,
      "pnl": 251.3,
      "reason": "Dropped from top picks"
    },
    {
      "date": "2026-03-10",
      "ticker": "XOM",
      "action": "SELL",
      "shares": 66,
      "price": 150.76,
      "value": 9950.16,
      "pnl": 0.0,
      "reason": "Dropped from top picks"
    },
    {
      "date": "2026-03-10",
      "ticker": "GLD",
      "action": "SELL",
      "shares": 21,
      "price": 466.13,
      "value": 9788.73,
      "pnl": 0.0,
      "reason": "Dropped from top picks"
    },
    {
      "date": "2026-03-10",
      "ticker": "KLAC",
      "action": "BUY",
      "shares": 4,
      "price": 1429.1,
      "value": 5716.4,
      "pnl": null,
      "pred_pct": 9.68,
      "confidence": 0.575,
      "reason": "Top pick #1, conf=57%, pred=+9.7%, alloc=14%"
    },
    {
      "date": "2026-03-10",
      "ticker": "MDB",
      "action": "BUY",
      "shares": 10,
      "price": 271.74,
      "value": 2717.4,
      "pnl": null,
      "pred_pct": 6.33,
      "confidence": 0.725,
      "reason": "Top pick #2, conf=72%, pred=+6.3%, alloc=6%"
    },
    {
      "date": "2026-03-10",
      "ticker": "XOM",
      "action": "BUY",
      "shares": 66,
      "price": 150.44,
      "value": 9929.04,
      "pnl": null,
      "pred_pct": 4.3,
      "confidence": 0.575,
      "reason": "Top pick #3, conf=57%, pred=+4.3%"
    },
    {
      "date": "2026-03-10",
      "ticker": "CVX",
      "action": "BUY",
      "shares": 52,
      "price": 189.44,
      "value": 9850.88,
      "pnl": null,
      "pred_pct": 2.41,
      "confidence": 0.75,
      "reason": "Top pick #5, conf=75%, pred=+2.4%, alloc=36%"
    },
    {
      "date": "2026-03-11",
      "ticker": "BAC",
      "action": "SELL",
      "shares": 200,
      "price": 48.52,
      "value": 9704.0,
      "pnl": -258.0,
      "reason": "Dropped from top picks"
    },
    {
      "date": "2026-03-11",
      "ticker": "KLAC",
      "action": "SELL",
      "shares": 4,
      "price": 1465.0,
      "value": 5860.0,
      "pnl": 143.6,
      "reason": "Dropped from top picks"
    },
    {
      "date": "2026-03-11",
      "ticker": "MDB",
      "action": "SELL",
      "shares": 10,
      "price": 270.57,
      "value": 2705.7,
      "pnl": -11.7,
      "reason": "Dropped from top picks"
    },
    {
      "date": "2026-03-11",
      "ticker": "XLE",
      "action": "BUY",
      "shares": 176,
      "price": 56.98,
      "value": 10028.48,
      "pnl": null,
      "pred_pct": 1.87,
      "confidence": 0.65,
      "reason": "Top pick #2, conf=65%, pred=+1.9%, alloc=24%"
    },
    {
      "date": "2026-03-11",
      "ticker": "GLD",
      "action": "BUY",
      "shares": 21,
      "price": 476.24,
      "value": 10001.04,
      "pnl": null,
      "pred_pct": 2.33,
      "confidence": 0.55,
      "reason": "Top pick #4, conf=55%, pred=+2.3%, alloc=21%"
    },
    {
      "date": "2026-03-11",
      "ticker": "SMCI",
      "action": "BUY",
      "shares": 171,
      "price": 31.79,
      "value": 5436.09,
      "pnl": null,
      "pred_pct": 0.64,
      "confidence": 0.55,
      "reason": "Top pick #5, conf=55%, pred=+0.6%, alloc=11%"
    },
    {
      "date": "2026-03-12",
      "ticker": "CVX",
      "action": "SELL",
      "shares": 52,
      "price": 196.97,
      "value": 10242.44,
      "pnl": 391.56,
      "reason": "Take-profit: +4.0% reached target +2.4%"
    },
    {
      "date": "2026-03-12",
      "ticker": "SMCI",
      "action": "SELL",
      "shares": 171,
      "price": 30.9,
      "value": 5283.9,
      "pnl": -152.19,
      "reason": "Dropped from top picks"
    },
    {
      "date": "2026-03-12",
      "ticker": "CVX",
      "action": "BUY",
      "shares": 51,
      "price": 196.97,
      "value": 10045.47,
      "pnl": null,
      "pred_pct": 0.87,
      "confidence": 0.65,
      "reason": "Top pick #4, conf=65%, pred=+0.9%, alloc=22%"
    },
    {
      "date": "2026-03-13",
      "ticker": "AVGO",
      "action": "BUY",
      "shares": 24,
      "price": 322.16,
      "value": 7731.84,
      "pnl": null,
      "pred_pct": 0.55,
      "confidence": 0.625,
      "reason": "Top pick #5, conf=62%, pred=+0.6%, alloc=16%"
    },
    {
      "date": "2026-03-16",
      "ticker": "XOM",
      "action": "SELL",
      "shares": 66,
      "price": 157.23,
      "value": 10377.18,
      "pnl": 448.14,
      "reason": "Take-profit: +4.5% reached target +4.3%"
    },
    {
      "date": "2026-03-16",
      "ticker": "GLD",
      "action": "SELL",
      "shares": 21,
      "price": 460.43,
      "value": 9669.03,
      "pnl": -332.01,
      "reason": "Dropped from top picks"
    },
    {
      "date": "2026-03-16",
      "ticker": "AVGO",
      "action": "SELL",
      "shares": 24,
      "price": 324.92,
      "value": 7798.08,
      "pnl": 66.24,
      "reason": "Signal bearish"
    },
    {
      "date": "2026-03-16",
      "ticker": "XOM",
      "action": "BUY",
      "shares": 64,
      "price": 157.23,
      "value": 10062.72,
      "pnl": null,
      "pred_pct": 1.99,
      "confidence": 0.6,
      "reason": "Top pick #3, conf=60%, pred=+2.0%, alloc=20%"
    },
    {
      "date": "2026-03-17",
      "ticker": "XLE",
      "action": "SELL",
      "shares": 176,
      "price": 58.51,
      "value": 10297.76,
      "pnl": 269.28,
      "reason": "Take-profit: +2.7% reached target +1.9%"
    },
    {
      "date": "2026-03-17",
      "ticker": "XLE",
      "action": "BUY",
      "shares": 174,
      "price": 58.51,
      "value": 10180.74,
      "pnl": null,
      "pred_pct": 1.33,
      "confidence": 0.7,
      "reason": "Top pick #1, conf=70%, pred=+1.3%, alloc=49%"
    },
    {
      "date": "2026-03-19",
      "ticker": "XLE",
      "action": "SELL",
      "shares": 174,
      "price": 59.36,
      "value": 10328.64,
      "pnl": 147.9,
      "reason": "Take-profit: +1.5% reached target +1.3%"
    },
    {
      "date": "2026-03-19",
      "ticker": "XLE",
      "action": "BUY",
      "shares": 172,
      "price": 59.36,
      "value": 10209.92,
      "pnl": null,
      "pred_pct": 1.27,
      "confidence": 0.7,
      "reason": "Top pick #2, conf=70%, pred=+1.3%, alloc=37%"
    },
    {
      "date": "2026-03-23",
      "ticker": "XOM",
      "action": "SELL",
      "shares": 64,
      "price": 161.13,
      "value": 10312.32,
      "pnl": 249.6,
      "reason": "Take-profit: +2.5% reached target +2.0%"
    },
    {
      "date": "2026-03-23",
      "ticker": "XOM",
      "action": "BUY",
      "shares": 64,
      "price": 161.13,
      "value": 10312.32,
      "pnl": null,
      "pred_pct": 2.07,
      "confidence": 0.65,
      "reason": "Top pick #1, conf=65%, pred=+2.1%, alloc=38%"
    },
    {
      "date": "2026-03-24",
      "ticker": "XLE",
      "action": "SELL",
      "shares": 172,
      "price": 60.84,
      "value": 10464.48,
      "pnl": 254.56,
      "reason": "Take-profit: +2.5% reached target +1.3%"
    },
    {
      "date": "2026-03-24",
      "ticker": "XOM",
      "action": "SELL",
      "shares": 64,
      "price": 165.38,
      "value": 10584.32,
      "pnl": 272.0,
      "reason": "Take-profit: +2.6% reached target +2.1%"
    },
    {
      "date": "2026-03-24",
      "ticker": "MU",
      "action": "BUY",
      "shares": 13,
      "price": 395.53,
      "value": 5141.89,
      "pnl": null,
      "pred_pct": 8.23,
      "confidence": 0.55,
      "reason": "Top pick #1, conf=55%, pred=+8.2%, alloc=10%"
    },
    {
      "date": "2026-03-24",
      "ticker": "XLE",
      "action": "BUY",
      "shares": 171,
      "price": 60.84,
      "value": 10403.64,
      "pnl": null,
      "pred_pct": 0.82,
      "confidence": 0.7,
      "reason": "Top pick #2, conf=70%, pred=+0.8%, alloc=41%"
    },
    {
      "date": "2026-03-24",
      "ticker": "XOM",
      "action": "BUY",
      "shares": 63,
      "price": 165.38,
      "value": 10418.94,
      "pnl": null,
      "pred_pct": 0.95,
      "confidence": 0.65,
      "reason": "Top pick #3, conf=65%, pred=+0.9%, alloc=24%"
    },
    {
      "date": "2026-03-25",
      "ticker": "MU",
      "action": "SELL",
      "shares": 13,
      "price": 382.09,
      "value": 4967.17,
      "pnl": -174.72,
      "reason": "Dropped from top picks"
    },
    {
      "date": "2026-03-27",
      "ticker": "CVX",
      "action": "SELL",
      "shares": 51,
      "price": 211.15,
      "value": 10768.65,
      "pnl": 723.18,
      "reason": "Signal bearish"
    },
    {
      "date": "2026-03-27",
      "ticker": "XLE",
      "action": "SELL",
      "shares": 171,
      "price": 62.56,
      "value": 10697.76,
      "pnl": 294.12,
      "reason": "Signal bearish"
    },
    {
      "date": "2026-03-27",
      "ticker": "XOM",
      "action": "SELL",
      "shares": 63,
      "price": 170.99,
      "value": 10772.37,
      "pnl": 353.43,
      "reason": "Signal bearish"
    },
    {
      "date": "2026-03-30",
      "ticker": "XLE",
      "action": "BUY",
      "shares": 170,
      "price": 61.96,
      "value": 10533.2,
      "pnl": null,
      "pred_pct": 0.96,
      "confidence": 0.8,
      "reason": "Top pick #1, conf=80%, pred=+1.0%, alloc=60%"
    },
    {
      "date": "2026-03-30",
      "ticker": "CVX",
      "action": "BUY",
      "shares": 50,
      "price": 210.71,
      "value": 10535.5,
      "pnl": null,
      "pred_pct": 0.46,
      "confidence": 0.8,
      "reason": "Top pick #2, conf=80%, pred=+0.5%, alloc=40%"
    },
    {
      "date": "2026-03-31",
      "ticker": "XOM",
      "action": "BUY",
      "shares": 62,
      "price": 169.66,
      "value": 10518.92,
      "pnl": null,
      "pred_pct": 1.04,
      "confidence": 0.8,
      "reason": "Top pick #3, conf=80%, pred=+1.0%, alloc=25%"
    },
    {
      "date": "2026-04-08",
      "ticker": "CVX",
      "action": "SELL",
      "shares": 50,
      "price": 192.89,
      "value": 9644.5,
      "pnl": -891.0,
      "reason": "Trailing stop: -8.5% from $210.71 peak"
    },
    {
      "date": "2026-04-08",
      "ticker": "CVX",
      "action": "BUY",
      "shares": 52,
      "price": 192.89,
      "value": 10030.28,
      "pnl": null,
      "pred_pct": 5.46,
      "confidence": 0.625,
      "reason": "Top pick #2, conf=62%, pred=+5.5%, alloc=30%"
    },
    {
      "date": "2026-04-09",
      "ticker": "XOM",
      "action": "SELL",
      "shares": 62,
      "price": 155.04,
      "value": 9612.48,
      "pnl": -906.44,
      "reason": "Trailing stop: -8.6% from $169.66 peak"
    },
    {
      "date": "2026-04-09",
      "ticker": "XOM",
      "action": "BUY",
      "shares": 64,
      "price": 155.04,
      "value": 9922.56,
      "pnl": null,
      "pred_pct": 5.49,
      "confidence": 0.65,
      "reason": "Top pick #2, conf=65%, pred=+5.5%, alloc=22%"
    },
    {
      "date": "2026-04-09",
      "ticker": "NET",
      "action": "BUY",
      "shares": 44,
      "price": 193.05,
      "value": 8494.2,
      "pnl": null,
      "pred_pct": 6.3,
      "confidence": 0.55,
      "reason": "Top pick #4, conf=55%, pred=+6.3%, alloc=17%"
    },
    {
      "date": "2026-04-10",
      "ticker": "XLE",
      "action": "SELL",
      "shares": 170,
      "price": 56.94,
      "value": 9679.8,
      "pnl": -853.4,
      "reason": "Trailing stop: -8.1% from $61.96 peak"
    },
    {
      "date": "2026-04-10",
      "ticker": "NET",
      "action": "SELL",
      "shares": 44,
      "price": 166.99,
      "value": 7347.56,
      "pnl": -1146.64,
      "reason": "Trailing stop: -13.5% from $193.05 peak"
    },
    {
      "date": "2026-04-10",
      "ticker": "CVX",
      "action": "SELL",
      "shares": 52,
      "price": 188.55,
      "value": 9804.6,
      "pnl": -225.68,
      "reason": "Dropped from top picks"
    },
    {
      "date": "2026-04-10",
      "ticker": "XOM",
      "action": "SELL",
      "shares": 64,
      "price": 152.51,
      "value": 9760.64,
      "pnl": -161.92,
      "reason": "Dropped from top picks"
    },
    {
      "date": "2026-04-17",
      "ticker": "NFLX",
      "action": "BUY",
      "shares": 100,
      "price": 97.31,
      "value": 9731.0,
      "pnl": null,
      "pred_pct": 5.31,
      "confidence": 0.8,
      "reason": "Top pick #1, conf=80%, pred=+5.3%, alloc=100%"
    },
    {
      "date": "2026-04-23",
      "ticker": "NFLX",
      "action": "SELL",
      "shares": 100,
      "price": 92.82,
      "value": 9282.0,
      "pnl": -449.0,
      "reason": "Dropped from top picks"
    },
    {
      "date": "2026-04-30",
      "ticker": "PYPL",
      "action": "BUY",
      "shares": 192,
      "price": 50.14,
      "value": 9626.88,
      "pnl": null,
      "pred_pct": 0.83,
      "confidence": 0.6,
      "reason": "Top pick #1, conf=60%, pred=+0.8%, alloc=100%"
    },
    {
      "date": "2026-05-05",
      "ticker": "PYPL",
      "action": "SELL",
      "shares": 192,
      "price": 46.49,
      "value": 8926.08,
      "pnl": -700.8,
      "reason": "Dropped from top picks"
    },
    {
      "date": "2026-05-08",
      "ticker": "BAC",
      "action": "BUY",
      "shares": 185,
      "price": 51.31,
      "value": 9492.35,
      "pnl": null,
      "pred_pct": 0.83,
      "confidence": 0.55,
      "reason": "Top pick #1, conf=55%, pred=+0.8%, alloc=100%"
    },
    {
      "date": "2026-05-11",
      "ticker": "BAC",
      "action": "SELL",
      "shares": 185,
      "price": 50.55,
      "value": 9351.75,
      "pnl": -140.6,
      "reason": "Dropped from top picks"
    },
    {
      "date": "2026-05-11",
      "ticker": "AMZN",
      "action": "BUY",
      "shares": 35,
      "price": 268.99,
      "value": 9414.65,
      "pnl": null,
      "pred_pct": 1.1,
      "confidence": 0.55,
      "reason": "Top pick #1, conf=55%, pred=+1.1%, alloc=60%"
    },
    {
      "date": "2026-05-11",
      "ticker": "ARM",
      "action": "BUY",
      "shares": 28,
      "price": 212.65,
      "value": 5954.2,
      "pnl": null,
      "pred_pct": 2.04,
      "confidence": 0.6,
      "reason": "Top pick #2, conf=60%, pred=+2.0%, alloc=13%"
    },
    {
      "date": "2026-05-11",
      "ticker": "KLAC",
      "action": "BUY",
      "shares": 5,
      "price": 1845.19,
      "value": 9225.95,
      "pnl": null,
      "pred_pct": 0.97,
      "confidence": 0.55,
      "reason": "Top pick #3, conf=55%, pred=+1.0%, alloc=27%"
    },
    {
      "date": "2026-05-12",
      "ticker": "AMZN",
      "action": "SELL",
      "shares": 35,
      "price": 265.82,
      "value": 9303.7,
      "pnl": -110.95,
      "reason": "Dropped from top picks"
    },
    {
      "date": "2026-05-12",
      "ticker": "ARM",
      "action": "SELL",
      "shares": 28,
      "price": 207.92,
      "value": 5821.76,
      "pnl": -132.44,
      "reason": "Dropped from top picks"
    },
    {
      "date": "2026-05-12",
      "ticker": "AVGO",
      "action": "BUY",
      "shares": 22,
      "price": 419.3,
      "value": 9224.6,
      "pnl": null,
      "pred_pct": 1.74,
      "confidence": 0.575,
      "reason": "Top pick #1, conf=57%, pred=+1.7%, alloc=55%"
    },
    {
      "date": "2026-05-14",
      "ticker": "AVGO",
      "action": "SELL",
      "shares": 22,
      "price": 439.79,
      "value": 9675.38,
      "pnl": 450.78,
      "reason": "Take-profit: +4.9% reached target +1.7%"
    },
    {
      "date": "2026-05-15",
      "ticker": "IWM",
      "action": "BUY",
      "shares": 34,
      "price": 277.6,
      "value": 9438.4,
      "pnl": null,
      "pred_pct": 0.99,
      "confidence": 0.65,
      "reason": "Top pick #2, conf=65%, pred=+1.0%, alloc=46%"
    },
    {
      "date": "2026-05-15",
      "ticker": "ARKK",
      "action": "BUY",
      "shares": 126,
      "price": 74.9,
      "value": 9437.4,
      "pnl": null,
      "pred_pct": 2.06,
      "confidence": 0.6,
      "reason": "Top pick #3, conf=60%, pred=+2.1%, alloc=20%"
    },
    {
      "date": "2026-05-15",
      "ticker": "ARM",
      "action": "BUY",
      "shares": 16,
      "price": 209.16,
      "value": 3346.56,
      "pnl": null,
      "pred_pct": 5.34,
      "confidence": 0.625,
      "reason": "Top pick #4, conf=62%, pred=+5.3%, alloc=7%"
    },
    {
      "date": "2026-05-15",
      "ticker": "COIN",
      "action": "BUY",
      "shares": 24,
      "price": 195.43,
      "value": 4690.32,
      "pnl": null,
      "pred_pct": 2.58,
      "confidence": 0.55,
      "reason": "Top pick #5, conf=55%, pred=+2.6%, alloc=10%"
    },
    {
      "date": "2026-05-18",
      "ticker": "ARM",
      "action": "SELL",
      "shares": 16,
      "price": 215.12,
      "value": 3441.92,
      "pnl": 95.36,
      "reason": "Dropped from top picks"
    },
    {
      "date": "2026-05-18",
      "ticker": "COIN",
      "action": "SELL",
      "shares": 24,
      "price": 189.44,
      "value": 4546.56,
      "pnl": -143.76,
      "reason": "Dropped from top picks"
    },
    {
      "date": "2026-05-18",
      "ticker": "AMAT",
      "action": "BUY",
      "shares": 13,
      "price": 413.57,
      "value": 5376.41,
      "pnl": null,
      "pred_pct": 2.38,
      "confidence": 0.65,
      "reason": "Top pick #4, conf=65%, pred=+2.4%, alloc=12%"
    },
    {
      "date": "2026-05-18",
      "ticker": "SOXX",
      "action": "BUY",
      "shares": 8,
      "price": 495.87,
      "value": 3966.96,
      "pnl": null,
      "pred_pct": 2.19,
      "confidence": 0.6,
      "reason": "Top pick #5, conf=60%, pred=+2.2%, alloc=9%"
    },
    {
      "date": "2026-05-19",
      "ticker": "KLAC",
      "action": "SELL",
      "shares": 5,
      "price": 1740.58,
      "value": 8702.9,
      "pnl": -523.05,
      "reason": "Trailing stop: -8.0% from $1892.94 peak"
    },
    {
      "date": "2026-05-19",
      "ticker": "AMAT",
      "action": "SELL",
      "shares": 13,
      "price": 406.91,
      "value": 5289.83,
      "pnl": -86.58,
      "reason": "Dropped from top picks"
    },
    {
      "date": "2026-05-19",
      "ticker": "SOXX",
      "action": "SELL",
      "shares": 8,
      "price": 496.74,
      "value": 3973.92,
      "pnl": 6.96,
      "reason": "Dropped from top picks"
    },
    {
      "date": "2026-05-19",
      "ticker": "KLAC",
      "action": "BUY",
      "shares": 3,
      "price": 1740.58,
      "value": 5221.74,
      "pnl": null,
      "pred_pct": 5.27,
      "confidence": 0.6,
      "reason": "Top pick #2, conf=60%, pred=+5.3%, alloc=13%"
    },
    {
      "date": "2026-05-19",
      "ticker": "GS",
      "action": "BUY",
      "shares": 10,
      "price": 928.74,
      "value": 9287.4,
      "pnl": null,
      "pred_pct": 1.7,
      "confidence": 0.65,
      "reason": "Top pick #3, conf=65%, pred=+1.7%, alloc=26%"
    },
    {
      "date": "2026-05-19",
      "ticker": "LRCX",
      "action": "BUY",
      "shares": 14,
      "price": 273.38,
      "value": 3827.32,
      "pnl": null,
      "pred_pct": 3.43,
      "confidence": 0.6,
      "reason": "Top pick #5, conf=60%, pred=+3.4%, alloc=8%"
    },
    {
      "date": "2026-05-20",
      "ticker": "GS",
      "action": "SELL",
      "shares": 10,
      "price": 982.12,
      "value": 9821.2,
      "pnl": 533.8,
      "reason": "Take-profit: +5.7% reached target +1.7%"
    },
    {
      "date": "2026-05-20",
      "ticker": "LRCX",
      "action": "SELL",
      "shares": 14,
      "price": 292.09,
      "value": 4089.26,
      "pnl": 261.94,
      "reason": "Take-profit: +6.8% reached target +3.4%"
    },
    {
      "date": "2026-05-20",
      "ticker": "ARKK",
      "action": "SELL",
      "shares": 126,
      "price": 75.84,
      "value": 9555.84,
      "pnl": 118.44,
      "reason": "Dropped from top picks"
    },
    {
      "date": "2026-05-20",
      "ticker": "UNH",
      "action": "BUY",
      "shares": 25,
      "price": 383.3,
      "value": 9582.5,
      "pnl": null,
      "pred_pct": 2.82,
      "confidence": 0.625,
      "reason": "Top pick #1, conf=62%, pred=+2.8%, alloc=29%"
    },
    {
      "date": "2026-05-20",
      "ticker": "GOOGL",
      "action": "BUY",
      "shares": 19,
      "price": 388.91,
      "value": 7389.29,
      "pnl": null,
      "pred_pct": 1.72,
      "confidence": 0.55,
      "reason": "Top pick #4, conf=55%, pred=+1.7%, alloc=16%"
    },
    {
      "date": "2026-05-20",
      "ticker": "COIN",
      "action": "BUY",
      "shares": 25,
      "price": 191.29,
      "value": 4782.25,
      "pnl": null,
      "pred_pct": 2.23,
      "confidence": 0.55,
      "reason": "Top pick #5, conf=55%, pred=+2.2%, alloc=10%"
    },
    {
      "date": "2026-05-21",
      "ticker": "KLAC",
      "action": "SELL",
      "shares": 3,
      "price": 1842.18,
      "value": 5526.54,
      "pnl": 304.8,
      "reason": "Take-profit: +5.8% reached target +5.3%"
    },
    {
      "date": "2026-05-21",
      "ticker": "GOOGL",
      "action": "SELL",
      "shares": 19,
      "price": 387.66,
      "value": 7365.54,
      "pnl": -23.75,
      "reason": "Dropped from top picks"
    },
    {
      "date": "2026-05-21",
      "ticker": "COIN",
      "action": "SELL",
      "shares": 25,
      "price": 193.56,
      "value": 4839.0,
      "pnl": 56.75,
      "reason": "Dropped from top picks"
    },
    {
      "date": "2026-05-21",
      "ticker": "TXN",
      "action": "BUY",
      "shares": 31,
      "price": 298.39,
      "value": 9250.09,
      "pnl": null,
      "pred_pct": 1.75,
      "confidence": 0.6,
      "reason": "Top pick #2, conf=60%, pred=+1.8%, alloc=20%"
    },
    {
      "date": "2026-05-21",
      "ticker": "KLAC",
      "action": "BUY",
      "shares": 3,
      "price": 1842.18,
      "value": 5526.54,
      "pnl": null,
      "pred_pct": 2.7,
      "confidence": 0.55,
      "reason": "Top pick #3, conf=55%, pred=+2.7%, alloc=12%"
    },
    {
      "date": "2026-05-21",
      "ticker": "SOXX",
      "action": "BUY",
      "shares": 8,
      "price": 524.71,
      "value": 4197.68,
      "pnl": null,
      "pred_pct": 0.76,
      "confidence": 0.55,
      "reason": "Top pick #5, conf=55%, pred=+0.8%, alloc=9%"
    },
    {
      "date": "2026-05-22",
      "ticker": "TXN",
      "action": "SELL",
      "shares": 31,
      "price": 309.21,
      "value": 9585.51,
      "pnl": 335.42,
      "reason": "Take-profit: +3.6% reached target +1.8%"
    },
    {
      "date": "2026-05-22",
      "ticker": "IWM",
      "action": "SELL",
      "shares": 34,
      "price": 285.12,
      "value": 9694.08,
      "pnl": 255.68,
      "reason": "Dropped from top picks"
    },
    {
      "date": "2026-05-22",
      "ticker": "SOXX",
      "action": "SELL",
      "shares": 8,
      "price": 537.33,
      "value": 4298.64,
      "pnl": 100.96,
      "reason": "Signal bearish"
    },
    {
      "date": "2026-05-22",
      "ticker": "NVDA",
      "action": "BUY",
      "shares": 45,
      "price": 215.33,
      "value": 9689.85,
      "pnl": null,
      "pred_pct": 1.9,
      "confidence": 0.65,
      "reason": "Top pick #2, conf=65%, pred=+1.9%, alloc=27%"
    },
    {
      "date": "2026-05-26",
      "ticker": "KLAC",
      "action": "SELL",
      "shares": 3,
      "price": 2011.39,
      "value": 6034.17,
      "pnl": 507.63,
      "reason": "Take-profit: +9.2% reached target +2.7%"
    },
    {
      "date": "2026-05-26",
      "ticker": "MSFT",
      "action": "BUY",
      "shares": 23,
      "price": 416.03,
      "value": 9568.69,
      "pnl": null,
      "pred_pct": 0.74,
      "confidence": 0.55,
      "reason": "Top pick #3, conf=55%, pred=+0.7%, alloc=41%"
    },
    {
      "date": "2026-05-27",
      "ticker": "UNH",
      "action": "SELL",
      "shares": 25,
      "price": 384.01,
      "value": 9600.25,
      "pnl": 17.75,
      "reason": "Dropped from top picks"
    },
    {
      "date": "2026-05-27",
      "ticker": "MSFT",
      "action": "SELL",
      "shares": 23,
      "price": 412.67,
      "value": 9491.41,
      "pnl": -77.28,
      "reason": "Dropped from top picks"
    },
    {
      "date": "2026-05-27",
      "ticker": "SPY",
      "action": "BUY",
      "shares": 13,
      "price": 750.46,
      "value": 9755.98,
      "pnl": null,
      "pred_pct": 0.46,
      "confidence": 0.575,
      "reason": "Top pick #2, conf=57%, pred=+0.5%, alloc=58%"
    },
    {
      "date": "2026-05-27",
      "ticker": "TXN",
      "action": "BUY",
      "shares": 25,
      "price": 317.45,
      "value": 7936.25,
      "pnl": null,
      "pred_pct": 1.43,
      "confidence": 0.625,
      "reason": "Top pick #3, conf=62%, pred=+1.4%, alloc=16%"
    },
    {
      "date": "2026-05-27",
      "ticker": "SMH",
      "action": "BUY",
      "shares": 9,
      "price": 595.5,
      "value": 5359.5,
      "pnl": null,
      "pred_pct": 0.7,
      "confidence": 0.55,
      "reason": "Top pick #4, conf=55%, pred=+0.7%, alloc=12%"
    },
    {
      "date": "2026-05-28",
      "ticker": "NVDA",
      "action": "SELL",
      "shares": 45,
      "price": 214.25,
      "value": 9641.25,
      "pnl": -48.6,
      "reason": "Dropped from top picks"
    },
    {
      "date": "2026-05-28",
      "ticker": "SPY",
      "action": "SELL",
      "shares": 13,
      "price": 754.6,
      "value": 9809.8,
      "pnl": 53.82,
      "reason": "Dropped from top picks"
    },
    {
      "date": "2026-05-28",
      "ticker": "KLAC",
      "action": "BUY",
      "shares": 3,
      "price": 1927.63,
      "value": 5782.89,
      "pnl": null,
      "pred_pct": 2.81,
      "confidence": 0.55,
      "reason": "Top pick #2, conf=55%, pred=+2.8%, alloc=15%"
    },
    {
      "date": "2026-05-28",
      "ticker": "V",
      "action": "BUY",
      "shares": 30,
      "price": 324.95,
      "value": 9748.5,
      "pnl": null,
      "pred_pct": 0.55,
      "confidence": 0.675,
      "reason": "Top pick #3, conf=68%, pred=+0.6%, alloc=47%"
    },
    {
      "date": "2026-05-29",
      "ticker": "KLAC",
      "action": "SELL",
      "shares": 3,
      "price": 1921.71,
      "value": 5765.13,
      "pnl": -17.76,
      "reason": "Dropped from top picks"
    },
    {
      "date": "2026-05-29",
      "ticker": "INTC",
      "action": "BUY",
      "shares": 23,
      "price": 114.68,
      "value": 2637.64,
      "pnl": null,
      "pred_pct": 8.87,
      "confidence": 0.575,
      "reason": "Top pick #2, conf=57%, pred=+8.9%, alloc=5%"
    },
    {
      "date": "2026-05-29",
      "ticker": "VTI",
      "action": "BUY",
      "shares": 26,
      "price": 372.54,
      "value": 9686.04,
      "pnl": null,
      "pred_pct": 0.31,
      "confidence": 0.55,
      "reason": "Top pick #4, conf=55%, pred=+0.3%, alloc=39%"
    },
    {
      "date": "2026-06-01",
      "ticker": "SMH",
      "action": "SELL",
      "shares": 9,
      "price": 607.81,
      "value": 5470.29,
      "pnl": 110.79,
      "reason": "Dropped from top picks"
    },
    {
      "date": "2026-06-01",
      "ticker": "SPY",
      "action": "BUY",
      "shares": 12,
      "price": 758.54,
      "value": 9102.48,
      "pnl": null,
      "pred_pct": 0.31,
      "confidence": 0.6,
      "reason": "Top pick #4, conf=60%, pred=+0.3%, alloc=39%"
    },
    {
      "date": "2026-06-02",
      "ticker": "INTC",
      "action": "SELL",
      "shares": 23,
      "price": 107.93,
      "value": 2482.39,
      "pnl": -155.25,
      "reason": "Dropped from top picks"
    },
    {
      "date": "2026-06-02",
      "ticker": "SPY",
      "action": "SELL",
      "shares": 12,
      "price": 758.54,
      "value": 9102.48,
      "pnl": 0.0,
      "reason": "Dropped from top picks"
    },
    {
      "date": "2026-06-02",
      "ticker": "IWM",
      "action": "BUY",
      "shares": 33,
      "price": 291.66,
      "value": 9624.78,
      "pnl": null,
      "pred_pct": 1.03,
      "confidence": 0.55,
      "reason": "Top pick #3, conf=55%, pred=+1.0%, alloc=25%"
    },
    {
      "date": "2026-06-03",
      "ticker": "V",
      "action": "SELL",
      "shares": 30,
      "price": 312.4,
      "value": 9372.0,
      "pnl": -376.5,
      "reason": "Dropped from top picks"
    },
    {
      "date": "2026-06-03",
      "ticker": "SPY",
      "action": "BUY",
      "shares": 12,
      "price": 754.24,
      "value": 9050.88,
      "pnl": null,
      "pred_pct": 1.11,
      "confidence": 0.6,
      "reason": "Top pick #3, conf=60%, pred=+1.1%, alloc=32%"
    },
    {
      "date": "2026-06-03",
      "ticker": "DIA",
      "action": "BUY",
      "shares": 19,
      "price": 508.26,
      "value": 9656.94,
      "pnl": null,
      "pred_pct": 0.88,
      "confidence": 0.7,
      "reason": "Top pick #4, conf=70%, pred=+0.9%, alloc=24%"
    },
    {
      "date": "2026-06-04",
      "ticker": "IWM",
      "action": "SELL",
      "shares": 33,
      "price": 292.01,
      "value": 9636.33,
      "pnl": 11.55,
      "reason": "Dropped from top picks"
    },
    {
      "date": "2026-06-04",
      "ticker": "DIA",
      "action": "SELL",
      "shares": 19,
      "price": 516.7,
      "value": 9817.3,
      "pnl": 160.36,
      "reason": "Signal bearish"
    },
    {
      "date": "2026-06-04",
      "ticker": "AVGO",
      "action": "BUY",
      "shares": 7,
      "price": 418.91,
      "value": 2932.37,
      "pnl": null,
      "pred_pct": 8.7,
      "confidence": 0.6,
      "reason": "Top pick #1, conf=60%, pred=+8.7%, alloc=7%"
    },
    {
      "date": "2026-06-04",
      "ticker": "QQQ",
      "action": "BUY",
      "shares": 8,
      "price": 740.61,
      "value": 5924.88,
      "pnl": null,
      "pred_pct": 1.44,
      "confidence": 0.625,
      "reason": "Top pick #5, conf=62%, pred=+1.4%, alloc=12%"
    },
    {
      "date": "2026-06-05",
      "ticker": "TXN",
      "action": "SELL",
      "shares": 25,
      "price": 285.06,
      "value": 7126.5,
      "pnl": -809.75,
      "reason": "Trailing stop: -10.2% from $317.45 peak"
    },
    {
      "date": "2026-06-05",
      "ticker": "XLK",
      "action": "BUY",
      "shares": 18,
      "price": 180.3,
      "value": 3245.4,
      "pnl": null,
      "pred_pct": 5.01,
      "confidence": 0.7,
      "reason": "Top pick #5, conf=70%, pred=+5.0%, alloc=7%"
    },
    {
      "date": "2026-06-08",
      "ticker": "XLK",
      "action": "SELL",
      "shares": 18,
      "price": 184.18,
      "value": 3315.24,
      "pnl": 69.84,
      "reason": "Dropped from top picks"
    },
    {
      "date": "2026-06-08",
      "ticker": "AAPL",
      "action": "BUY",
      "shares": 31,
      "price": 301.54,
      "value": 9347.74,
      "pnl": null,
      "pred_pct": 3.35,
      "confidence": 0.55,
      "reason": "Top pick #4, conf=55%, pred=+3.4%, alloc=25%"
    },
    {
      "date": "2026-06-09",
      "ticker": "AVGO",
      "action": "SELL",
      "shares": 7,
      "price": 392.16,
      "value": 2745.12,
      "pnl": -187.25,
      "reason": "Dropped from top picks"
    },
    {
      "date": "2026-06-09",
      "ticker": "AAPL",
      "action": "SELL",
      "shares": 31,
      "price": 290.55,
      "value": 9007.05,
      "pnl": -340.69,
      "reason": "Dropped from top picks"
    },
    {
      "date": "2026-06-09",
      "ticker": "XLK",
      "action": "BUY",
      "shares": 18,
      "price": 180.77,
      "value": 3253.86,
      "pnl": null,
      "pred_pct": 5.2,
      "confidence": 0.65,
      "reason": "Top pick #4, conf=65%, pred=+5.2%, alloc=7%"
    },
    {
      "date": "2026-06-09",
      "ticker": "AMD",
      "action": "BUY",
      "shares": 7,
      "price": 475.51,
      "value": 3328.54,
      "pnl": null,
      "pred_pct": 10.07,
      "confidence": 0.65,
      "reason": "Top pick #5, conf=65%, pred=+10.1%, alloc=8%"
    },
    {
      "date": "2026-06-11",
      "ticker": "AMD",
      "action": "SELL",
      "shares": 7,
      "price": 488.45,
      "value": 3419.15,
      "pnl": 90.58,
      "reason": "Dropped from top picks"
    },
    {
      "date": "2026-06-11",
      "ticker": "APP",
      "action": "BUY",
      "shares": 9,
      "price": 478.57,
      "value": 4307.13,
      "pnl": null,
      "pred_pct": 8.87,
      "confidence": 0.625,
      "reason": "Top pick #4, conf=62%, pred=+8.9%, alloc=9%"
    },
    {
      "date": "2026-06-12",
      "ticker": "APP",
      "action": "SELL",
      "shares": 9,
      "price": 496.77,
      "value": 4470.93,
      "pnl": 163.8,
      "reason": "Dropped from top picks"
    },
    {
      "date": "2026-06-12",
      "ticker": "UNH",
      "action": "BUY",
      "shares": 23,
      "price": 408.52,
      "value": 9395.96,
      "pnl": null,
      "pred_pct": 3.89,
      "confidence": 0.55,
      "reason": "Top pick #4, conf=55%, pred=+3.9%, alloc=22%"
    },
    {
      "date": "2026-06-15",
      "ticker": "XLK",
      "action": "SELL",
      "shares": 18,
      "price": 191.79,
      "value": 3452.22,
      "pnl": 198.36,
      "reason": "Take-profit: +6.1% reached target +5.2%"
    },
    {
      "date": "2026-06-15",
      "ticker": "XLK",
      "action": "BUY",
      "shares": 17,
      "price": 191.79,
      "value": 3260.43,
      "pnl": null,
      "pred_pct": 2.89,
      "confidence": 0.55,
      "reason": "Top pick #5, conf=55%, pred=+2.9%, alloc=7%"
    },
    {
      "date": "2026-06-16",
      "ticker": "XLK",
      "action": "SELL",
      "shares": 17,
      "price": 186.44,
      "value": 3169.48,
      "pnl": -90.95,
      "reason": "Dropped from top picks"
    },
    {
      "date": "2026-06-16",
      "ticker": "AMD",
      "action": "BUY",
      "shares": 6,
      "price": 507.29,
      "value": 3043.74,
      "pnl": null,
      "pred_pct": 8.77,
      "confidence": 0.55,
      "reason": "Top pick #5, conf=55%, pred=+8.8%, alloc=7%"
    },
    {
      "date": "2026-06-17",
      "ticker": "AMD",
      "action": "SELL",
      "shares": 6,
      "price": 512.48,
      "value": 3074.88,
      "pnl": 31.14,
      "reason": "Dropped from top picks"
    },
    {
      "date": "2026-06-17",
      "ticker": "XLK",
      "action": "BUY",
      "shares": 17,
      "price": 185.8,
      "value": 3158.6,
      "pnl": null,
      "pred_pct": 4.85,
      "confidence": 0.55,
      "reason": "Top pick #5, conf=55%, pred=+4.8%, alloc=7%"
    },
    {
      "date": "2026-06-18",
      "ticker": "QQQ",
      "action": "SELL",
      "shares": 8,
      "price": 740.62,
      "value": 5924.96,
      "pnl": 0.08,
      "reason": "Dropped from top picks"
    },
    {
      "date": "2026-06-18",
      "ticker": "XLK",
      "action": "SELL",
      "shares": 17,
      "price": 191.44,
      "value": 3254.48,
      "pnl": 95.88,
      "reason": "Dropped from top picks"
    },
    {
      "date": "2026-06-18",
      "ticker": "FTNT",
      "action": "BUY",
      "shares": 34,
      "price": 144.73,
      "value": 4920.82,
      "pnl": null,
      "pred_pct": 5.72,
      "confidence": 0.625,
      "reason": "Top pick #4, conf=62%, pred=+5.7%, alloc=10%"
    },
    {
      "date": "2026-06-18",
      "ticker": "DIA",
      "action": "BUY",
      "shares": 18,
      "price": 515.52,
      "value": 9279.36,
      "pnl": null,
      "pred_pct": 1.61,
      "confidence": 0.6,
      "reason": "Top pick #5, conf=60%, pred=+1.6%, alloc=22%"
    },
    {
      "date": "2026-06-22",
      "ticker": "SPY",
      "action": "SELL",
      "shares": 12,
      "price": 744.39,
      "value": 8932.68,
      "pnl": -118.2,
      "reason": "Dropped from top picks"
    },
    {
      "date": "2026-06-22",
      "ticker": "DIA",
      "action": "SELL",
      "shares": 18,
      "price": 517.08,
      "value": 9307.44,
      "pnl": 28.08,
      "reason": "Dropped from top picks"
    },
    {
      "date": "2026-06-22",
      "ticker": "CRWD",
      "action": "BUY",
      "shares": 6,
      "price": 675.44,
      "value": 4052.64,
      "pnl": null,
      "pred_pct": 7.81,
      "confidence": 0.575,
      "reason": "Top pick #4, conf=57%, pred=+7.8%, alloc=9%"
    },
    {
      "date": "2026-06-22",
      "ticker": "QQQ",
      "action": "BUY",
      "shares": 9,
      "price": 737.95,
      "value": 6641.55,
      "pnl": null,
      "pred_pct": 3.36,
      "confidence": 0.55,
      "reason": "Top pick #5, conf=55%, pred=+3.4%, alloc=15%"
    },
    {
      "date": "2026-06-23",
      "ticker": "FTNT",
      "action": "SELL",
      "shares": 34,
      "price": 148.0,
      "value": 5032.0,
      "pnl": 111.18,
      "reason": "Dropped from top picks"
    },
    {
      "date": "2026-06-23",
      "ticker": "CRWD",
      "action": "SELL",
      "shares": 6,
      "price": 680.92,
      "value": 4085.52,
      "pnl": 32.88,
      "reason": "Dropped from top picks"
    },
    {
      "date": "2026-06-23",
      "ticker": "XLK",
      "action": "BUY",
      "shares": 22,
      "price": 184.19,
      "value": 4052.18,
      "pnl": null,
      "pred_pct": 5.94,
      "confidence": 0.55,
      "reason": "Top pick #4, conf=55%, pred=+5.9%, alloc=9%"
    },
    {
      "date": "2026-06-23",
      "ticker": "AMD",
      "action": "BUY",
      "shares": 6,
      "price": 519.85,
      "value": 3119.1,
      "pnl": null,
      "pred_pct": 9.43,
      "confidence": 0.55,
      "reason": "Top pick #5, conf=55%, pred=+9.4%, alloc=7%"
    },
    {
      "date": "2026-06-24",
      "ticker": "VTI",
      "action": "SELL",
      "shares": 26,
      "price": 363.65,
      "value": 9454.9,
      "pnl": -231.14,
      "reason": "Dropped from top picks"
    },
    {
      "date": "2026-06-24",
      "ticker": "QQQ",
      "action": "SELL",
      "shares": 9,
      "price": 710.62,
      "value": 6395.58,
      "pnl": -245.97,
      "reason": "Dropped from top picks"
    },
    {
      "date": "2026-06-24",
      "ticker": "XLK",
      "action": "SELL",
      "shares": 22,
      "price": 183.05,
      "value": 4027.1,
      "pnl": -25.08,
      "reason": "Dropped from top picks"
    },
    {
      "date": "2026-06-24",
      "ticker": "AMD",
      "action": "SELL",
      "shares": 6,
      "price": 519.74,
      "value": 3118.44,
      "pnl": -0.66,
      "reason": "Dropped from top picks"
    },
    {
      "date": "2026-06-24",
      "ticker": "INTC",
      "action": "BUY",
      "shares": 23,
      "price": 131.65,
      "value": 3027.95,
      "pnl": null,
      "pred_pct": 8.76,
      "confidence": 0.65,
      "reason": "Top pick #2, conf=65%, pred=+8.8%, alloc=6%"
    },
    {
      "date": "2026-06-24",
      "ticker": "PANW",
      "action": "BUY",
      "shares": 18,
      "price": 285.26,
      "value": 5134.68,
      "pnl": null,
      "pred_pct": 4.9,
      "confidence": 0.675,
      "reason": "Top pick #3, conf=68%, pred=+4.9%, alloc=11%"
    },
    {
      "date": "2026-06-24",
      "ticker": "DIA",
      "action": "BUY",
      "shares": 18,
      "price": 518.52,
      "value": 9333.36,
      "pnl": null,
      "pred_pct": 1.19,
      "confidence": 0.575,
      "reason": "Top pick #4, conf=57%, pred=+1.2%, alloc=43%"
    },
    {
      "date": "2026-06-24",
      "ticker": "GS",
      "action": "BUY",
      "shares": 6,
      "price": 1076.91,
      "value": 6461.46,
      "pnl": null,
      "pred_pct": 2.16,
      "confidence": 0.675,
      "reason": "Top pick #5, conf=68%, pred=+2.2%, alloc=14%"
    },
    {
      "date": "2026-06-25",
      "ticker": "PANW",
      "action": "SELL",
      "shares": 18,
      "price": 293.09,
      "value": 5275.62,
      "pnl": 140.94,
      "reason": "Dropped from top picks"
    },
    {
      "date": "2026-06-25",
      "ticker": "GS",
      "action": "SELL",
      "shares": 6,
      "price": 1065.09,
      "value": 6390.54,
      "pnl": -70.92,
      "reason": "Dropped from top picks"
    },
    {
      "date": "2026-06-25",
      "ticker": "AMD",
      "action": "BUY",
      "shares": 7,
      "price": 532.57,
      "value": 3727.99,
      "pnl": null,
      "pred_pct": 9.35,
      "confidence": 0.55,
      "reason": "Top pick #2, conf=55%, pred=+9.3%, alloc=9%"
    },
    {
      "date": "2026-06-25",
      "ticker": "SMH",
      "action": "BUY",
      "shares": 6,
      "price": 636.88,
      "value": 3821.28,
      "pnl": null,
      "pred_pct": 5.43,
      "confidence": 0.55,
      "reason": "Top pick #5, conf=55%, pred=+5.4%, alloc=9%"
    }
  ],
  "daily_values": [
    {
      "date": "2026-03-06",
      "value": 50000.0,
      "cash": 50000.0,
      "positions_value": 0.0,
      "spy_close": null
    },
    {
      "date": "2026-03-06",
      "value": 50000.0,
      "cash": 582.76,
      "positions_value": 49417.24,
      "spy_close": null
    },
    {
      "date": "2026-03-10",
      "value": 49844.8,
      "cash": 12051.08,
      "positions_value": 37793.72,
      "spy_close": 678.27
    },
    {
      "date": "2026-03-11",
      "value": 50298.14,
      "cash": 4855.17,
      "positions_value": 45442.97,
      "spy_close": 676.33
    },
    {
      "date": "2026-03-12",
      "value": 50440.73,
      "cash": 10336.04,
      "positions_value": 40104.69,
      "spy_close": 666.06
    },
    {
      "date": "2026-03-13",
      "value": 50510.62,
      "cash": 2604.2,
      "positions_value": 47906.42,
      "spy_close": 662.29
    },
    {
      "date": "2026-03-16",
      "value": 50677.73,
      "cash": 20385.77,
      "positions_value": 30291.96,
      "spy_close": 669.03
    },
    {
      "date": "2026-03-17",
      "value": 50943.84,
      "cash": 20502.79,
      "positions_value": 30441.05,
      "spy_close": 670.79
    },
    {
      "date": "2026-03-18",
      "value": 50884.48,
      "cash": 20502.79,
      "positions_value": 30381.69,
      "spy_close": 661.43
    },
    {
      "date": "2026-03-19",
      "value": 51227.11,
      "cash": 20621.51,
      "positions_value": 30605.6,
      "spy_close": 659.8
    },
    {
      "date": "2026-03-20",
      "value": 51329.94,
      "cash": 20621.51,
      "positions_value": 30708.43,
      "spy_close": 648.57
    },
    {
      "date": "2026-03-23",
      "value": 51655.9,
      "cash": 20621.51,
      "positions_value": 31034.39,
      "spy_close": 655.38
    },
    {
      "date": "2026-03-24",
      "value": 52216.6,
      "cash": 15705.84,
      "positions_value": 36510.76,
      "spy_close": 653.18
    },
    {
      "date": "2026-03-25",
      "value": 51778.51,
      "cash": 20673.01,
      "positions_value": 31105.5,
      "spy_close": 656.82
    },
    {
      "date": "2026-03-26",
      "value": 52212.31,
      "cash": 20673.01,
      "positions_value": 31539.3,
      "spy_close": 645.09
    },
    {
      "date": "2026-03-27",
      "value": 52911.79,
      "cash": 52911.79,
      "positions_value": 0.0,
      "spy_close": 634.09
    },
    {
      "date": "2026-03-30",
      "value": 52911.79,
      "cash": 31843.09,
      "positions_value": 21068.7,
      "spy_close": 631.97
    },
    {
      "date": "2026-03-31",
      "value": 52602.29,
      "cash": 21324.17,
      "positions_value": 31278.12,
      "spy_close": 650.34
    },
    {
      "date": "2026-04-01",
      "value": 51187.93,
      "cash": 21324.17,
      "positions_value": 29863.76,
      "spy_close": 655.24
    },
    {
      "date": "2026-04-02",
      "value": 51307.95,
      "cash": 21324.17,
      "positions_value": 29983.78,
      "spy_close": 655.83
    },
    {
      "date": "2026-04-06",
      "value": 51541.71,
      "cash": 21324.17,
      "positions_value": 30217.54,
      "spy_close": 658.93
    },
    {
      "date": "2026-04-07",
      "value": 51790.79,
      "cash": 21324.17,
      "positions_value": 30466.62,
      "spy_close": 659.22
    },
    {
      "date": "2026-04-08",
      "value": 50522.81,
      "cash": 20938.39,
      "positions_value": 29584.42,
      "spy_close": 676.01
    },
    {
      "date": "2026-04-09",
      "value": 50195.69,
      "cash": 12134.11,
      "positions_value": 38061.58,
      "spy_close": 679.91
    },
    {
      "date": "2026-04-10",
      "value": 48726.71,
      "cash": 48726.71,
      "positions_value": 0.0,
      "spy_close": 679.46
    },
    {
      "date": "2026-04-13",
      "value": 48726.71,
      "cash": 48726.71,
      "positions_value": 0.0,
      "spy_close": 686.1
    },
    {
      "date": "2026-04-14",
      "value": 48726.71,
      "cash": 48726.71,
      "positions_value": 0.0,
      "spy_close": 694.46
    },
    {
      "date": "2026-04-15",
      "value": 48726.71,
      "cash": 48726.71,
      "positions_value": 0.0,
      "spy_close": 699.94
    },
    {
      "date": "2026-04-16",
      "value": 48726.71,
      "cash": 48726.71,
      "positions_value": 0.0,
      "spy_close": 701.66
    },
    {
      "date": "2026-04-17",
      "value": 48726.71,
      "cash": 38995.71,
      "positions_value": 9731.0,
      "spy_close": 710.14
    },
    {
      "date": "2026-04-20",
      "value": 48478.71,
      "cash": 38995.71,
      "positions_value": 9483.0,
      "spy_close": 708.72
    },
    {
      "date": "2026-04-21",
      "value": 48253.71,
      "cash": 38995.71,
      "positions_value": 9258.0,
      "spy_close": 704.08
    },
    {
      "date": "2026-04-22",
      "value": 48319.71,
      "cash": 38995.71,
      "positions_value": 9324.0,
      "spy_close": 711.21
    },
    {
      "date": "2026-04-23",
      "value": 48277.71,
      "cash": 48277.71,
      "positions_value": 0.0,
      "spy_close": 708.45
    },
    {
      "date": "2026-04-24",
      "value": 48277.71,
      "cash": 48277.71,
      "positions_value": 0.0,
      "spy_close": 713.94
    },
    {
      "date": "2026-04-27",
      "value": 48277.71,
      "cash": 48277.71,
      "positions_value": 0.0,
      "spy_close": 715.17
    },
    {
      "date": "2026-04-28",
      "value": 48277.71,
      "cash": 48277.71,
      "positions_value": 0.0,
      "spy_close": 711.69
    },
    {
      "date": "2026-04-29",
      "value": 48277.71,
      "cash": 48277.71,
      "positions_value": 0.0,
      "spy_close": 711.58
    },
    {
      "date": "2026-04-30",
      "value": 48277.71,
      "cash": 38650.83,
      "positions_value": 9626.88,
      "spy_close": 718.66
    },
    {
      "date": "2026-05-01",
      "value": 48335.31,
      "cash": 38650.83,
      "positions_value": 9684.48,
      "spy_close": 720.65
    },
    {
      "date": "2026-05-04",
      "value": 48325.71,
      "cash": 38650.83,
      "positions_value": 9674.88,
      "spy_close": 718.01
    },
    {
      "date": "2026-05-05",
      "value": 47576.91,
      "cash": 47576.91,
      "positions_value": 0.0,
      "spy_close": 723.77
    },
    {
      "date": "2026-05-06",
      "value": 47576.91,
      "cash": 47576.91,
      "positions_value": 0.0,
      "spy_close": 733.83
    },
    {
      "date": "2026-05-07",
      "value": 47576.91,
      "cash": 47576.91,
      "positions_value": 0.0,
      "spy_close": 731.58
    },
    {
      "date": "2026-05-08",
      "value": 47576.91,
      "cash": 38084.56,
      "positions_value": 9492.35,
      "spy_close": 737.62
    },
    {
      "date": "2026-05-11",
      "value": 47436.31,
      "cash": 22841.51,
      "positions_value": 24594.8,
      "spy_close": 739.3
    },
    {
      "date": "2026-05-12",
      "value": 47023.72,
      "cash": 28742.37,
      "positions_value": 18281.35,
      "spy_close": 738.18
    },
    {
      "date": "2026-05-13",
      "value": 47160.3,
      "cash": 28742.37,
      "positions_value": 18417.93,
      "spy_close": 742.31
    },
    {
      "date": "2026-05-14",
      "value": 47882.45,
      "cash": 38417.75,
      "positions_value": 9464.7,
      "spy_close": 748.17
    },
    {
      "date": "2026-05-15",
      "value": 47439.35,
      "cash": 11505.07,
      "positions_value": 35934.28,
      "spy_close": 739.17
    },
    {
      "date": "2026-05-18",
      "value": 47047.04,
      "cash": 10150.18,
      "positions_value": 36896.86,
      "spy_close": 738.65
    },
    {
      "date": "2026-05-19",
      "value": 46702.67,
      "cash": 9780.37,
      "positions_value": 36922.3,
      "spy_close": 733.73
    },
    {
      "date": "2026-05-20",
      "value": 48250.66,
      "cash": 11492.63,
      "positions_value": 36758.03,
      "spy_close": 741.25
    },
    {
      "date": "2026-05-21",
      "value": 48390.37,
      "cash": 10249.4,
      "positions_value": 38140.97,
      "spy_close": 742.72
    },
    {
      "date": "2026-05-22",
      "value": 49204.52,
      "cash": 24137.78,
      "positions_value": 25066.74,
      "spy_close": 745.64
    },
    {
      "date": "2026-05-26",
      "value": 49262.15,
      "cash": 20603.26,
      "positions_value": 28658.89,
      "spy_close": 750.59
    },
    {
      "date": "2026-05-27",
      "value": 49261.92,
      "cash": 16643.19,
      "positions_value": 32618.73,
      "spy_close": 750.46
    },
    {
      "date": "2026-05-28",
      "value": 49391.46,
      "cash": 20562.85,
      "positions_value": 28828.61,
      "spy_close": 754.6
    },
    {
      "date": "2026-05-29",
      "value": 49151.15,
      "cash": 14004.3,
      "positions_value": 35146.85,
      "spy_close": 756.48
    },
    {
      "date": "2026-06-01",
      "value": 48710.68,
      "cash": 10372.11,
      "positions_value": 38338.57,
      "spy_close": 758.54
    },
    {
      "date": "2026-06-02",
      "value": 48912.94,
      "cash": 12332.2,
      "positions_value": 36580.74,
      "spy_close": null
    },
    {
      "date": "2026-06-03",
      "value": 48574.96,
      "cash": 2996.38,
      "positions_value": 45578.58,
      "spy_close": 754.24
    },
    {
      "date": "2026-06-04",
      "value": 48877.22,
      "cash": 13592.76,
      "positions_value": 35284.46,
      "spy_close": 757.09
    },
    {
      "date": "2026-06-05",
      "value": 47358.33,
      "cash": 17473.86,
      "positions_value": 29884.47,
      "spy_close": 737.55
    },
    {
      "date": "2026-06-08",
      "value": 47640.72,
      "cash": 11441.36,
      "positions_value": 36199.36,
      "spy_close": 739.22
    },
    {
      "date": "2026-06-09",
      "value": 47156.19,
      "cash": 16611.13,
      "positions_value": 30545.06,
      "spy_close": 737.05
    },
    {
      "date": "2026-06-10",
      "value": 46520.99,
      "cash": 16611.13,
      "positions_value": 29909.86,
      "spy_close": 725.43
    },
    {
      "date": "2026-06-11",
      "value": 47389.94,
      "cash": 15723.15,
      "positions_value": 31666.79,
      "spy_close": 737.76
    },
    {
      "date": "2026-06-12",
      "value": 47717.56,
      "cash": 10798.12,
      "positions_value": 36919.44,
      "spy_close": 741.75
    },
    {
      "date": "2026-06-15",
      "value": 48400.0,
      "cash": 10989.91,
      "positions_value": 37410.09,
      "spy_close": 754.83
    },
    {
      "date": "2026-06-16",
      "value": 48007.8,
      "cash": 11115.65,
      "positions_value": 36892.15,
      "spy_close": 750.33
    },
    {
      "date": "2026-06-17",
      "value": 47561.08,
      "cash": 11031.93,
      "positions_value": 36529.15,
      "spy_close": 740.96
    },
    {
      "date": "2026-06-18",
      "value": 48014.07,
      "cash": 6011.19,
      "positions_value": 42002.88,
      "spy_close": 746.74
    },
    {
      "date": "2026-06-22",
      "value": 48137.27,
      "cash": 13557.12,
      "positions_value": 34580.15,
      "spy_close": 744.39
    },
    {
      "date": "2026-06-23",
      "value": 47966.44,
      "cash": 15503.36,
      "positions_value": 32463.08,
      "spy_close": 733.58
    },
    {
      "date": "2026-06-24",
      "value": 47832.78,
      "cash": 14541.93,
      "positions_value": 33290.85,
      "spy_close": 733.24
    },
    {
      "date": "2026-06-25",
      "value": 48167.97,
      "cash": 18658.82,
      "positions_value": 29509.15,
      "spy_close": 734.3
    }
  ],
  "last_updated": "2026-06-25",
  "created": "2026-03-06",
  "all_time_high": 52911.79
}